p2pb2bapi/__init__.py
p2pb2bapi-1.1.dist-info/METADATA
p2pb2bapi-1.1.dist-info/WHEEL
p2pb2bapi-1.1.dist-info/top_level.txt
p2pb2bapi-1.1.dist-info/RECORD
