Metadata-Version: 2.1
Name: p2pb2bapi
Version: 1.1
Summary: Wrapper for p2pb2b exchange API
Home-page: https://github.com/kirillkuzin/p2pb2b
Author: Kirill Kuzin
Author-email: offkirillkuzin@gmail.com
License: UNKNOWN
Platform: UNKNOWN
Classifier: Programming Language :: Python :: 3
Classifier: License :: OSI Approved :: MIT License
Classifier: Operating System :: OS Independent
